dapr/ext/strands/__init__.py
dapr/ext/strands/dapr_session_manager.py
dapr/ext/strands/version.py
dapr_ext_strands_dev-1.16.0.dev60.dist-info/licenses/LICENSE
dapr_ext_strands_dev-1.16.0.dev60.dist-info/METADATA
dapr_ext_strands_dev-1.16.0.dev60.dist-info/WHEEL
dapr_ext_strands_dev-1.16.0.dev60.dist-info/top_level.txt
dapr_ext_strands_dev-1.16.0.dev60.dist-info/RECORD
