Metadata-Version: 2.4
Name: dapr-ext-strands-dev
Version: 1.16.0.dev60
Summary: The developmental release for the Dapr Session Manager extension for Strands Agents
Home-page: https://dapr.io/
Author: Dapr Authors
Author-email: daprweb@microsoft.com
License: Apache
Project-URL: Documentation, https://github.com/dapr/docs
Project-URL: Source, https://github.com/dapr/python-sdk
Classifier: Development Status :: 5 - Production/Stable
Classifier: Intended Audience :: Developers
Classifier: License :: OSI Approved :: Apache Software License
Classifier: Operating System :: OS Independent
Classifier: Programming Language :: Python
Classifier: Programming Language :: Python :: 3.10
Classifier: Programming Language :: Python :: 3.11
Classifier: Programming Language :: Python :: 3.12
Classifier: Programming Language :: Python :: 3.13
Classifier: Programming Language :: Python :: 3.14
Requires-Python: >=3.10
License-File: LICENSE
Requires-Dist: dapr>=1.16.1rc1
Requires-Dist: strands-agents
Requires-Dist: strands-agents-tools
Requires-Dist: python-ulid>=3.0.0
Requires-Dist: msgpack-python>=0.4.5
Dynamic: description
Dynamic: license-file
Dynamic: summary
